{"title":"멜론 ─ 최신앨범 ─ 국내","url":"https://www.melon.com/new/album/index.htm#params%5BareaFlg%5D=I&params%5BorderBy%5D=&po=pageObj&startIndex=1","favicon":"https://www.melon.com/new/album/favicon.ico","elements":[{"title":"고려거란전쟁 OST Part. 4","contents":"IYAGI (이야기)","link":"javascript:melon.link.goAlbumDetail('11411152');","retrieved":1706930047718,"image":"https://cdnimg.melon.co.kr/cm2/album/images/114/11/152/11411152_20240202113458_500.jpg/melon/resize/360/quality/80/optimize"},{"title":"미스터로또 베스트 PART34","contents":"<div class=\"thumb\">\n\t\t\t\t\t<a href=\"javascript:melon.link.goAlbumDetail('11411104');\" title=\"미스터로또 베스트 PART34 - 페이지 이동\" class=\"image_typeAll\">\n\t\t\t\t\t\t<img onerror=\"WEBPOCIMG.defaultAlbumImg(this);\" width=\"180\" height=\"180\" src=\"https://cdnimg.melon.co.kr/cm2/album/images/114/11/104/11411104_20240202112230_500.jpg/melon/resize/360/quality/80/optimize\" alt=\"\">\n\t\t\t\t\t\t<span class=\"bg_album_frame\"></span>\n\t\t\t\t\t</a>\n\t\t\t\t</div>\n\n\t\t\t\t\n\n\t\t\t\t<div class=\"entry\">\n\t\t\t\t\t<div class=\"info\">\n\t\t\t\t\t\t<span class=\"vdo_name\">[옴니버스]</span>\n\t\t\t\t\t\t<a href=\"javascript:melon.link.goAlbumDetail('11411104');\" class=\"ellipsis album_name\" title=\"미스터로또 베스트 PART34 - 페이지 이동\">미스터로또 베스트 PART34</a>\n\t\t\t\t\t\t<span class=\"ellipsis artist\">\n\t\t\t\t\t\t\tVarious Artists<span class=\"checkEllipsis\" style=\"display: none;\">Various Artists</span>\n\t\t\t\t\t\t</span>\n\t\t\t\t\t\t\n\t\t\t\t\t</div>\n\t\t\t\t\t<div class=\"meta\">\n\t\t\t\t\t\t<span class=\"reg_date\" title=\"발매일\">2024.02.03</span>\n\t\t\t\t\t\t<i class=\"bar\"></i>\n\t\t\t\t\t\t<button type=\"button\" class=\"button_etc like\" title=\"미스터로또 베스트 PART34 좋아요\" data-album-no=\"11411104\" data-album-menuid=\"18020123\"><span class=\"odd_span\">좋아요</span>\n<span class=\"cnt\"><strong class=\"none\">총건수</strong>536</span></button>\n\t\t\t\t\t\t<i class=\"bar\"></i>\n\t\t\t\t\t\t<span class=\"tot_song\" title=\"총 수록곡\">6곡</span>\n\t\t\t\t\t</div>\n\t\t\t\t\t<div class=\"wrap_btn_tb\">\n\t\t\t\t\t\t<button type=\"button\" onclick=\"melon.play.playAlbum('18020123','11411104');\" title=\"앨범듣기\" class=\"button_rbox\"><span class=\"button_icons type02 play\"></span><span class=\"cnt\">앨범듣기</span></button>\n\t\t\t\t\t\t<button type=\"button\" onclick=\"melon.buy.goBuyProduct('frm','11411104','3B0001','','0','18020123','1');\" title=\"앨범 다운로드\" class=\"button_rbox\"><span class=\"button_icons type02 download\"></span><span class=\"cnt\">앨범다운</span></button>\n\t\t\t\t\t\t\n\t\t\t\t\t\t<button type=\"button\" onclick=\"melon.buy.goPresentForAlbum('11411104', '', '18020123');\" title=\"선택된 곡 선물하기\" class=\"button_rbox\"><span class=\"button_icons type02 gift\"></span><span class=\"cnt\">선물</span></button>\n\t\t\t\t\t\t\n\t\t\t\t\t</div>\n\t\t\t\t</div>","link":"javascript:melon.link.goAlbumDetail('11411104');","retrieved":1706930047691,"image":"https://cdnimg.melon.co.kr/cm2/album/images/114/11/104/11411104_20240202112230_500.jpg/melon/resize/360/quality/80/optimize"},{"title":"C'MON (질러)","contents":"SUPER JUNIOR-L.S.S. (슈퍼주니어-L.S.S.)","link":"javascript:melon.link.goAlbumDetail('11411072');","retrieved":1706930047719,"image":"https://cdnimg.melon.co.kr/cm2/album/images/114/11/072/11411072_20240202110951_500.jpg/melon/resize/360/quality/80/optimize"},{"title":"Slow Dance","contents":"전채언","link":"javascript:melon.link.goAlbumDetail('11411038');","retrieved":1706930047720,"image":"https://cdnimg.melon.co.kr/cm2/album/images/114/11/038/11411038_20240202105724_500.jpg/melon/resize/360/quality/80/optimize"},{"title":"icansee","contents":"새벽","link":"javascript:melon.link.goAlbumDetail('11410901');","retrieved":1706930047721,"image":"https://cdnimg.melon.co.kr/cm2/album/images/114/10/901/11410901_20240202092355_500.jpg/melon/resize/360/quality/80/optimize"},{"title":"온통 너였다","contents":"이민석","link":"javascript:melon.link.goAlbumDetail('11410637');","retrieved":1706930047729,"image":"https://cdnimg.melon.co.kr/cm2/album/images/114/10/637/11410637_20240201153210_500.jpg/melon/resize/360/quality/80/optimize"},{"title":"김성규 (KIM SUNG KYU) Remake Digital Single Vol.3","contents":"김성규","link":"javascript:melon.link.goAlbumDetail('11410657');","retrieved":1706865207201,"image":"https://cdnimg.melon.co.kr/cm2/album/images/114/10/657/11410657_20240201160552_500.jpg/melon/resize/360/quality/80/optimize"},{"title":"True Love","contents":"BOBBY","link":"javascript:melon.link.goAlbumDetail('11410499');","retrieved":1706865207201,"image":"https://cdnimg.melon.co.kr/cm2/album/images/114/10/499/11410499_20240201143601_500.jpg/melon/resize/360/quality/80/optimize"},{"contents":"<a href=\"javascript:melon.link.goArtistDetail('742763');\" title=\"True Love 페이지 이동\" class=\"ellipsis\">BOBBY</a>","retrieved":1706948066728},{"contents":"<a href=\"javascript:melon.link.goArtistDetail('925515');\" title=\"True Love 페이지 이동\" class=\"ellipsis\">오반</a>","retrieved":1706948066729},{"title":"너를 위해","contents":"KCM","link":"javascript:melon.link.goAlbumDetail('11410654');","retrieved":1706865207209,"image":"https://cdnimg.melon.co.kr/cm2/album/images/114/10/654/11410654_20240201160000_500.jpg/melon/resize/360/quality/80/optimize"},{"title":"환승연애3 OST Part 6","contents":"<div class=\"thumb\">\n\t\t\t\t\t<a href=\"javascript:melon.link.goAlbumDetail('11410213');\" title=\"환승연애3 OST Part 6 - 페이지 이동\" class=\"image_typeAll\">\n\t\t\t\t\t\t<img onerror=\"WEBPOCIMG.defaultAlbumImg(this);\" width=\"180\" height=\"180\" src=\"https://cdnimg.melon.co.kr/cm2/album/images/114/10/213/11410213_20240201112319_500.jpg/melon/resize/360/quality/80/optimize\" alt=\"\">\n\t\t\t\t\t\t<span class=\"bg_album_frame\"></span>\n\t\t\t\t\t</a>\n\t\t\t\t</div>\n\n\t\t\t\t\n\n\t\t\t\t<div class=\"entry\">\n\t\t\t\t\t<div class=\"info\">\n\t\t\t\t\t\t<span class=\"vdo_name\">[옴니버스]</span>\n\t\t\t\t\t\t<a href=\"javascript:melon.link.goAlbumDetail('11410213');\" class=\"ellipsis album_name\" title=\"환승연애3 OST Part 6 - 페이지 이동\">환승연애3 OST Part 6</a>\n\t\t\t\t\t\t<span class=\"ellipsis artist\">\n\t\t\t\t\t\t\tVarious Artists<span class=\"checkEllipsis\" style=\"display: none;\">Various Artists</span>\n\t\t\t\t\t\t</span>\n\t\t\t\t\t\t\n\t\t\t\t\t</div>\n\t\t\t\t\t<div class=\"meta\">\n\t\t\t\t\t\t<span class=\"reg_date\" title=\"발매일\">2024.02.02</span>\n\t\t\t\t\t\t<i class=\"bar\"></i>\n\t\t\t\t\t\t<button type=\"button\" class=\"button_etc like\" title=\"환승연애3 OST Part 6 좋아요\" data-album-no=\"11410213\" data-album-menuid=\"18020123\"><span class=\"odd_span\">좋아요</span>\n<span class=\"cnt\"><strong class=\"none\">총건수</strong>50</span></button>\n\t\t\t\t\t\t<i class=\"bar\"></i>\n\t\t\t\t\t\t<span class=\"tot_song\" title=\"총 수록곡\">17곡</span>\n\t\t\t\t\t</div>\n\t\t\t\t\t<div class=\"wrap_btn_tb\">\n\t\t\t\t\t\t<button type=\"button\" onclick=\"melon.play.playAlbum('18020123','11410213');\" title=\"앨범듣기\" class=\"button_rbox\"><span class=\"button_icons type02 play\"></span><span class=\"cnt\">앨범듣기</span></button>\n\t\t\t\t\t\t<button type=\"button\" onclick=\"melon.buy.goBuyProduct('frm','11410213','3B0001','','0','18020123','1');\" title=\"앨범 다운로드\" class=\"button_rbox\"><span class=\"button_icons type02 download\"></span><span class=\"cnt\">앨범다운</span></button>\n\t\t\t\t\t\t\n\t\t\t\t\t\t<button type=\"button\" onclick=\"melon.buy.goPresentForAlbum('11410213', '', '18020123');\" title=\"선택된 곡 선물하기\" class=\"button_rbox\"><span class=\"button_icons type02 gift\"></span><span class=\"cnt\">선물</span></button>\n\t\t\t\t\t\t\n\t\t\t\t\t</div>\n\t\t\t\t</div>","link":"javascript:melon.link.goAlbumDetail('11410213');","retrieved":1706865207195,"image":"https://cdnimg.melon.co.kr/cm2/album/images/114/10/213/11410213_20240201112319_500.jpg/melon/resize/360/quality/80/optimize"},{"title":"I GOT YOU","contents":"TWICE (트와이스)","link":"javascript:melon.link.goAlbumDetail('11410399');","retrieved":1706854518107,"image":"https://cdnimg.melon.co.kr/cm2/album/images/114/10/399/11410399_20240201115656_500.jpg/melon/resize/360/quality/80/optimize"},{"title":"아름다운 이별","contents":"왁스","link":"javascript:melon.link.goAlbumDetail('11410130');","retrieved":1706865207213,"image":"https://cdnimg.melon.co.kr/cm2/album/images/114/10/130/11410130_20240201100557_500.jpg/melon/resize/360/quality/80/optimize"},{"title":"KINEMA","contents":"DPR ARTIC","link":"javascript:melon.link.goAlbumDetail('11410653');","retrieved":1706854518108,"image":"https://cdnimg.melon.co.kr/cm2/album/images/114/10/653/11410653_20240201155911_500.jpg/melon/resize/360/quality/80/optimize"},{"title":"그만하자","contents":"천승찬","link":"javascript:melon.link.goAlbumDetail('11411150');","retrieved":1706930047749,"image":"https://cdnimg.melon.co.kr/cm2/album/images/114/11/150/11411150_20240202113346_500.jpg/melon/resize/360/quality/80/optimize"},{"title":"모노드라마","contents":"톰너드 (Tomnerd)","link":"javascript:melon.link.goAlbumDetail('11410991');","retrieved":1706930047751,"image":"https://cdnimg.melon.co.kr/cm2/album/images/114/10/991/11410991_20240202104611_500.jpg/melon/resize/360/quality/80/optimize"},{"title":"자장가","contents":"19990619","link":"javascript:melon.link.goAlbumDetail('11410993');","retrieved":1706930047752,"image":"https://cdnimg.melon.co.kr/cm2/album/images/114/10/993/11410993_20240202104634_500.jpg/melon/resize/360/quality/80/optimize"},{"title":"가짜 공녀님의 만렙 토끼 OST Part.23","contents":"신민경","link":"javascript:melon.link.goAlbumDetail('11410933');","retrieved":1706930047754,"image":"https://cdnimg.melon.co.kr/cm2/album/images/114/10/933/11410933_20240202103205_500.jpg/melon/resize/360/quality/80/optimize"},{"title":"오늘을 기억해","contents":"원테이블 (One Table)","link":"javascript:melon.link.goAlbumDetail('11410907');","retrieved":1706930047756,"image":"https://cdnimg.melon.co.kr/cm2/album/images/114/10/907/11410907_20240202093315_500.jpg/melon/resize/360/quality/80/optimize"},{"title":"HOW TO LOVE?","contents":"김민철과 하야테","link":"javascript:melon.link.goAlbumDetail('11410218');","retrieved":1706865207213,"image":"https://cdnimg.melon.co.kr/cm2/album/images/114/10/218/11410218_20240201112705_500.jpg/melon/resize/360/quality/80/optimize"},{"title":"남과여 OST Part.3","contents":"g0nny (거니)","link":"javascript:melon.link.goAlbumDetail('11410422');","retrieved":1706865207214,"image":"https://cdnimg.melon.co.kr/cm2/album/images/114/10/422/11410422_20240201135416_500.jpg/melon/resize/360/quality/80/optimize"}]}