{"title":"Combined feed","url":"https://MusicReleaseKR.github.io/melon/all.xml","elements":[{"title":"현역가왕 준결승 1대1 라이벌전 (멜론 ─ 최신앨범 ─ 국내)","contents":"<div class=\"thumb\">\n\t\t\t\t\t<a href=\"javascript:melon.link.goAlbumDetail('11404163');\" title=\"현역가왕 준결승 1대1 라이벌전 - 페이지 이동\" class=\"image_typeAll\">\n\t\t\t\t\t\t<img onerror=\"WEBPOCIMG.defaultAlbumImg(this);\" width=\"180\" height=\"180\" src=\"https://cdnimg.melon.co.kr/cm2/album/images/114/04/163/11404163_20240123174729_500.jpg/melon/resize/360/quality/80/optimize\" alt=\"\">\n\t\t\t\t\t\t<span class=\"bg_album_frame\"></span>\n\t\t\t\t\t</a>\n\t\t\t\t</div>\n\n\t\t\t\t\n\n\t\t\t\t<div class=\"entry\">\n\t\t\t\t\t<div class=\"info\">\n\t\t\t\t\t\t<span class=\"vdo_name\">[옴니버스]</span>\n\t\t\t\t\t\t<a href=\"javascript:melon.link.goAlbumDetail('11404163');\" class=\"ellipsis album_name\" title=\"현역가왕 준결승 1대1 라이벌전 - 페이지 이동\">현역가왕 준결승 1대1 라이벌전</a>\n\t\t\t\t\t\t<span class=\"ellipsis artist\">\n\t\t\t\t\t\t\tVarious Artists<span class=\"checkEllipsis\" style=\"display: none;\">Various Artists</span>\n\t\t\t\t\t\t</span>\n\t\t\t\t\t\t\n\t\t\t\t\t</div>\n\t\t\t\t\t<div class=\"meta\">\n\t\t\t\t\t\t<span class=\"reg_date\" title=\"발매일\">2024.01.24</span>\n\t\t\t\t\t\t<i class=\"bar\"></i>\n\t\t\t\t\t\t<button type=\"button\" class=\"button_etc like\" title=\"현역가왕 준결승 1대1 라이벌전 좋아요\" data-album-no=\"11404163\" data-album-menuid=\"18020123\"><span class=\"odd_span\">좋아요</span>\n<span class=\"cnt\"><strong class=\"none\">총건수</strong>19</span></button>\n\t\t\t\t\t\t<i class=\"bar\"></i>\n\t\t\t\t\t\t<span class=\"tot_song\" title=\"총 수록곡\">28곡</span>\n\t\t\t\t\t</div>\n\t\t\t\t\t<div class=\"wrap_btn_tb\">\n\t\t\t\t\t\t<button type=\"button\" onclick=\"melon.play.playAlbum('18020123','11404163');\" title=\"앨범듣기\" class=\"button_rbox\"><span class=\"button_icons type02 play\"></span><span class=\"cnt\">앨범듣기</span></button>\n\t\t\t\t\t\t<button type=\"button\" onclick=\"melon.buy.goBuyProduct('frm','11404163','3B0001','','0','18020123','1');\" title=\"앨범 다운로드\" class=\"button_rbox\"><span class=\"button_icons type02 download\"></span><span class=\"cnt\">앨범다운</span></button>\n\t\t\t\t\t\t\n\t\t\t\t\t\t<button type=\"button\" onclick=\"melon.buy.goPresentForAlbum('11404163', '', '18020123');\" title=\"선택된 곡 선물하기\" class=\"button_rbox\"><span class=\"button_icons type02 gift\"></span><span class=\"cnt\">선물</span></button>\n\t\t\t\t\t\t\n\t\t\t\t\t</div>\n\t\t\t\t</div>","link":"javascript:melon.link.goAlbumDetail('11404163');","retrieved":1706066037286,"image":"https://cdnimg.melon.co.kr/cm2/album/images/114/04/163/11404163_20240123174729_500.jpg/melon/resize/360/quality/80/optimize"},{"title":"사랑 그 그리움3 (멜론 ─ 최신앨범 ─ 국내)","contents":"웅산","link":"javascript:melon.link.goAlbumDetail('11404152');","retrieved":1706066037297,"image":"https://cdnimg.melon.co.kr/cm2/album/images/114/04/152/11404152_20240123173346_500.jpg/melon/resize/360/quality/80/optimize"},{"title":"노놀 VOL 29. 윤정훈 ' 우리를 에워싼 꿈속에서 ' (멜론 ─ 최신앨범 ─ 국내)","contents":"윤정훈","link":"javascript:melon.link.goAlbumDetail('11404186');","retrieved":1706066037300,"image":"https://cdnimg.melon.co.kr/cm2/album/images/114/04/186/11404186_20240123175349_500.jpg/melon/resize/360/quality/80/optimize"},{"title":"너의 자리 (멜론 ─ 최신앨범 ─ 국내)","contents":"주예인","link":"javascript:melon.link.goAlbumDetail('11403982');","retrieved":1706066037300,"image":"https://cdnimg.melon.co.kr/cm2/album/images/114/03/982/11403982_20240123142717_500.jpg/melon/resize/360/quality/80/optimize"},{"title":"조금만 느리게 흘렀으면 좋겠어 (멜론 ─ 최신앨범 ─ 국내)","contents":"merrymerryseoul","link":"javascript:melon.link.goAlbumDetail('11404072');","retrieved":1706066037302,"image":"https://cdnimg.melon.co.kr/cm2/album/images/114/04/072/11404072_20240123165753_500.jpg/melon/resize/360/quality/80/optimize"},{"title":"사랑하지 말 걸 그랬어 (멜론 ─ 최신앨범 ─ 국내)","contents":"성수진","link":"javascript:melon.link.goAlbumDetail('11404084');","retrieved":1706066037302,"image":"https://cdnimg.melon.co.kr/cm2/album/images/114/04/084/11404084_20240123170904_500.jpg/melon/resize/360/quality/80/optimize"},{"title":"INSIDE OUT (멜론 ─ 최신앨범 ─ 국내)","contents":"설아 (우주소녀)","link":"javascript:melon.link.goAlbumDetail('11403460');","retrieved":1706001172063,"image":"https://cdnimg.melon.co.kr/cm2/album/images/114/03/460/11403460_20240122153416_500.jpg/melon/resize/360/quality/80/optimize"},{"title":"Slowly (Feat. 헤이즈) (멜론 ─ 최신앨범 ─ 국내)","contents":"I.M (아이엠)","link":"javascript:melon.link.goAlbumDetail('11403684');","retrieved":1706001172063,"image":"https://cdnimg.melon.co.kr/cm2/album/images/114/03/684/11403684_20240122235601_500.jpg/melon/resize/360/quality/80/optimize"},{"title":"나무가 될게 (멜론 ─ 최신앨범 ─ 국내)","contents":"박강수","link":"javascript:melon.link.goAlbumDetail('11403884');","retrieved":1706066037305,"image":"https://cdnimg.melon.co.kr/cm2/album/images/114/03/884/11403884_20240123112751_500.jpg/melon/resize/360/quality/80/optimize"},{"title":"미워 죽겠어 (멜론 ─ 최신앨범 ─ 국내)","contents":"동경","link":"javascript:melon.link.goAlbumDetail('11403833');","retrieved":1706066037306,"image":"https://cdnimg.melon.co.kr/cm2/album/images/114/03/833/11403833_20240123104753_500.jpg/melon/resize/360/quality/80/optimize"},{"title":"어떻게 우리 헤어질 수가 있어 (멜론 ─ 최신앨범 ─ 국내)","contents":"주현민","link":"javascript:melon.link.goAlbumDetail('11404164');","retrieved":1706066037307,"image":"https://cdnimg.melon.co.kr/cm2/album/images/114/04/164/11404164_20240123174808_500.jpg/melon/resize/360/quality/80/optimize"},{"title":"One Two (feat. CHERRY BOY 17) (멜론 ─ 최신앨범 ─ 국내)","contents":"TOKAI (토케이)","link":"javascript:melon.link.goAlbumDetail('11403994');","retrieved":1706066037308,"image":"https://cdnimg.melon.co.kr/cm2/album/images/114/03/994/11403994_20240123143536_500.jpg/melon/resize/360/quality/80/optimize"},{"title":"Giggles (멜론 ─ 최신앨범 ─ 국내)","contents":"홍다빈","link":"javascript:melon.link.goAlbumDetail('11345372');","retrieved":1706001172063,"image":"https://cdnimg.melon.co.kr/cm2/album/images/113/45/372/11345372_20240123132927_500.jpg/melon/resize/360/quality/80/optimize"},{"title":"Colors (멜론 ─ 최신앨범 ─ 국내)","contents":"컴 (COME)","link":"javascript:melon.link.goAlbumDetail('11403983');","retrieved":1706066037311,"image":"https://cdnimg.melon.co.kr/cm2/album/images/114/03/983/11403983_20240123142818_500.jpg/melon/resize/360/quality/80/optimize"},{"title":"내 남편과 결혼해줘 OST Part.4 (멜론 ─ 최신앨범 ─ 국내)","contents":"김소연","link":"javascript:melon.link.goAlbumDetail('11403506');","retrieved":1706001172065,"image":"https://cdnimg.melon.co.kr/cm2/album/images/114/03/506/11403506_20240122160328_500.jpg/melon/resize/360/quality/80/optimize"},{"title":"소냐의 뮤지컬 Page2 (멜론 ─ 최신앨범 ─ 국내)","contents":"소냐","link":"javascript:melon.link.goAlbumDetail('11403832');","retrieved":1706066037320,"image":"https://cdnimg.melon.co.kr/cm2/album/images/114/03/832/11403832_20240123104407_500.jpg/melon/resize/360/quality/80/optimize"},{"title":"비틀거리는 행복 (멜론 ─ 최신앨범 ─ 국내)","contents":"에몬","link":"javascript:melon.link.goAlbumDetail('11403880');","retrieved":1706066037321,"image":"https://cdnimg.melon.co.kr/cm2/album/images/114/03/880/11403880_20240123111407_500.jpg/melon/resize/360/quality/80/optimize"},{"title":"Sweet Dreamz (멜론 ─ 최신앨범 ─ 국내)","contents":"Hanbyeol (한별)","link":"javascript:melon.link.goAlbumDetail('11403510');","retrieved":1706066037331,"image":"https://cdnimg.melon.co.kr/cm2/album/images/114/03/510/11403510_20240122162407_500.jpg/melon/resize/360/quality/80/optimize"},{"title":"헤어지기 싫어 (멜론 ─ 최신앨범 ─ 국내)","contents":"유림","link":"javascript:melon.link.goAlbumDetail('11403563');","retrieved":1706001172066,"image":"https://cdnimg.melon.co.kr/cm2/album/images/114/03/563/11403563_20240122171242_500.jpg/melon/resize/360/quality/80/optimize"},{"title":"Wish (멜론 ─ 최신앨범 ─ 국내)","contents":"Ash-B (애쉬비)","link":"javascript:melon.link.goAlbumDetail('11403552');","retrieved":1706001172067,"image":"https://cdnimg.melon.co.kr/cm2/album/images/114/03/552/11403552_20240122171000_500.jpg/melon/resize/360/quality/80/optimize"}]}