{"title":"Combined feed","url":"https://MusicReleaseKR.github.io/melon/all.xml","elements":[{"title":"Sweet (멜론 ─ 최신앨범 ─ 국내)","contents":"더보이즈 (THE BOYZ)","link":"javascript:melon.link.goAlbumDetail('10985471');","retrieved":1655457417749,"image":"https://cdnimg.melon.co.kr/cm2/album/images/109/85/471/10985471_20220617110328_500.jpg/melon/resize/360/quality/80/optimize"},{"title":"닥터로이어 OST Part.2 (멜론 ─ 최신앨범 ─ 국내)","contents":"첸 (CHEN)","link":"javascript:melon.link.goAlbumDetail('10984537');","retrieved":1655457417749,"image":"https://cdnimg.melon.co.kr/cm2/album/images/109/84/537/10984537_20220615162729_500.jpg/melon/resize/360/quality/80/optimize"},{"title":"유미의 세포들 시즌2 OST Part 2 (멜론 ─ 최신앨범 ─ 국내)","contents":"죠지","link":"javascript:melon.link.goAlbumDetail('10985610');","retrieved":1655457417750,"image":"https://cdnimg.melon.co.kr/cm2/album/images/109/85/610/10985610_20220617122004_500.jpg/melon/resize/360/quality/80/optimize"},{"title":"서울체크인 OST Part 9 (멜론 ─ 최신앨범 ─ 국내)","contents":"종한 (JONGHAN)","link":"javascript:melon.link.goAlbumDetail('10985210');","retrieved":1655457417755,"image":"https://cdnimg.melon.co.kr/cm2/album/images/109/85/210/10985210_20220616154128_500.jpg/melon/resize/360/quality/80/optimize"},{"title":"형 (멜론 ─ 최신앨범 ─ 국내)","contents":"주석","link":"javascript:melon.link.goAlbumDetail('10985374');","retrieved":1655457417756,"image":"https://cdnimg.melon.co.kr/cm2/album/images/109/85/374/10985374_20220616181829_500.jpg/melon/resize/360/quality/80/optimize"},{"title":"국가가 부른다 Part16 (멜론 ─ 최신앨범 ─ 국내)","contents":"<div class=\"thumb\">\n\t\t\t\t\t<a href=\"javascript:melon.link.goAlbumDetail('10985213');\" title=\"국가가 부른다 Part16 - 페이지 이동\" class=\"image_typeAll\">\n\t\t\t\t\t\t<img onerror=\"WEBPOCIMG.defaultAlbumImg(this);\" src=\"https://cdnimg.melon.co.kr/cm2/album/images/109/85/213/10985213_20220616154347_500.jpg/melon/resize/360/quality/80/optimize\" alt=\"\" width=\"180\" height=\"180\">\n\t\t\t\t\t\t<span class=\"bg_album_frame\"></span>\n\t\t\t\t\t</a>\n\t\t\t\t</div>\n\n\t\t\t\t\n\n\t\t\t\t<div class=\"entry\">\n\t\t\t\t\t<div class=\"info\">\n\t\t\t\t\t\t<span class=\"vdo_name\">[옴니버스]</span>\n\t\t\t\t\t\t<a href=\"javascript:melon.link.goAlbumDetail('10985213');\" class=\"ellipsis album_name\" title=\"국가가 부른다 Part16 - 페이지 이동\">국가가 부른다 Part16</a>\n\t\t\t\t\t\t<span class=\"ellipsis artist\">\n\t\t\t\t\t\t\tVarious Artists<span class=\"checkEllipsis\" style=\"display: none;\">Various Artists</span>\n\t\t\t\t\t\t</span>\n\t\t\t\t\t\t\n\t\t\t\t\t</div>\n\t\t\t\t\t<div class=\"meta\">\n\t\t\t\t\t\t<span class=\"reg_date\" title=\"발매일\">2022.06.17</span>\n\t\t\t\t\t\t<i class=\"bar\"></i>\n\t\t\t\t\t\t<button type=\"button\" class=\"button_etc like\" title=\"국가가 부른다 Part16 좋아요\" data-album-no=\"10985213\" data-album-menuid=\"18020123\"><span class=\"odd_span\">좋아요</span>\n<span class=\"cnt\"><strong class=\"none\">총건수</strong>463</span></button>\n\t\t\t\t\t\t<i class=\"bar\"></i>\n\t\t\t\t\t\t<span class=\"tot_song\" title=\"총 수록곡\">6곡</span>\n\t\t\t\t\t</div>\n\t\t\t\t\t<div class=\"wrap_btn_tb\">\n\t\t\t\t\t\t<button type=\"button\" onclick=\"melon.play.playAlbum('18020123','10985213');\" title=\"앨범듣기\" class=\"button_rbox\"><span class=\"button_icons type02 play\"></span><span class=\"cnt\">앨범듣기</span></button>\n\t\t\t\t\t\t<button type=\"button\" onclick=\"melon.buy.goBuyProduct('frm','10985213','3B0001','','0','18020123','1');\" title=\"앨범 다운로드\" class=\"button_rbox\"><span class=\"button_icons type02 download\"></span><span class=\"cnt\">앨범다운</span></button>\n\t\t\t\t\t\t\n\t\t\t\t\t\t<button type=\"button\" onclick=\"melon.buy.goPresentForAlbum('10985213', '', '18020123');\" title=\"선택된 곡 선물하기\" class=\"button_rbox\"><span class=\"button_icons type02 gift\"></span><span class=\"cnt\">선물</span></button>\n\t\t\t\t\t\t\n\t\t\t\t\t</div>\n\t\t\t\t</div>","link":"javascript:melon.link.goAlbumDetail('10985213');","retrieved":1655436429095,"image":"https://cdnimg.melon.co.kr/cm2/album/images/109/85/213/10985213_20220616154347_500.jpg/melon/resize/360/quality/80/optimize"},{"title":"청춘스타 Part5 (멜론 ─ 최신앨범 ─ 국내)","contents":"<div class=\"thumb\">\n\t\t\t\t\t<a href=\"javascript:melon.link.goAlbumDetail('10985221');\" title=\"청춘스타 Part5 - 페이지 이동\" class=\"image_typeAll\">\n\t\t\t\t\t\t<img onerror=\"WEBPOCIMG.defaultAlbumImg(this);\" src=\"https://cdnimg.melon.co.kr/cm2/album/images/109/85/221/10985221_20220616154836_500.jpg/melon/resize/360/quality/80/optimize\" alt=\"\" width=\"180\" height=\"180\">\n\t\t\t\t\t\t<span class=\"bg_album_frame\"></span>\n\t\t\t\t\t</a>\n\t\t\t\t</div>\n\n\t\t\t\t\n\n\t\t\t\t<div class=\"entry\">\n\t\t\t\t\t<div class=\"info\">\n\t\t\t\t\t\t<span class=\"vdo_name\">[옴니버스]</span>\n\t\t\t\t\t\t<a href=\"javascript:melon.link.goAlbumDetail('10985221');\" class=\"ellipsis album_name\" title=\"청춘스타 Part5 - 페이지 이동\">청춘스타 Part5</a>\n\t\t\t\t\t\t<span class=\"ellipsis artist\">\n\t\t\t\t\t\t\tVarious Artists<span class=\"checkEllipsis\" style=\"display: none;\">Various Artists</span>\n\t\t\t\t\t\t</span>\n\t\t\t\t\t\t\n\t\t\t\t\t</div>\n\t\t\t\t\t<div class=\"meta\">\n\t\t\t\t\t\t<span class=\"reg_date\" title=\"발매일\">2022.06.17</span>\n\t\t\t\t\t\t<i class=\"bar\"></i>\n\t\t\t\t\t\t<button type=\"button\" class=\"button_etc like\" title=\"청춘스타 Part5 좋아요\" data-album-no=\"10985221\" data-album-menuid=\"18020123\"><span class=\"odd_span\">좋아요</span>\n<span class=\"cnt\"><strong class=\"none\">총건수</strong>26</span></button>\n\t\t\t\t\t\t<i class=\"bar\"></i>\n\t\t\t\t\t\t<span class=\"tot_song\" title=\"총 수록곡\">4곡</span>\n\t\t\t\t\t</div>\n\t\t\t\t\t<div class=\"wrap_btn_tb\">\n\t\t\t\t\t\t<button type=\"button\" onclick=\"melon.play.playAlbum('18020123','10985221');\" title=\"앨범듣기\" class=\"button_rbox\"><span class=\"button_icons type02 play\"></span><span class=\"cnt\">앨범듣기</span></button>\n\t\t\t\t\t\t<button type=\"button\" onclick=\"melon.buy.goBuyProduct('frm','10985221','3B0001','','0','18020123','1');\" title=\"앨범 다운로드\" class=\"button_rbox\"><span class=\"button_icons type02 download\"></span><span class=\"cnt\">앨범다운</span></button>\n\t\t\t\t\t\t\n\t\t\t\t\t\t<button type=\"button\" onclick=\"melon.buy.goPresentForAlbum('10985221', '', '18020123');\" title=\"선택된 곡 선물하기\" class=\"button_rbox\"><span class=\"button_icons type02 gift\"></span><span class=\"cnt\">선물</span></button>\n\t\t\t\t\t\t\n\t\t\t\t\t</div>\n\t\t\t\t</div>","link":"javascript:melon.link.goAlbumDetail('10985221');","retrieved":1655436429096,"image":"https://cdnimg.melon.co.kr/cm2/album/images/109/85/221/10985221_20220616154836_500.jpg/melon/resize/360/quality/80/optimize"},{"title":"GENE_SIS OST part 1: D_COMPOSE (멜론 ─ 최신앨범 ─ 국내)","contents":"SURAN (수란)","link":"javascript:melon.link.goAlbumDetail('10985167');","retrieved":1655436429115,"image":"https://cdnimg.melon.co.kr/cm2/album/images/109/85/167/10985167_20220616152052_500.jpg/melon/resize/360/quality/80/optimize"},{"title":"undefined (멜론 ─ 최신앨범 ─ 국내)","contents":"<a href=\"javascript:melon.link.goArtistDetail('792765');\" title=\"GENE_SIS OST part 1: D_COMPOSE 페이지 이동\" class=\"ellipsis\">SURAN (수란)</a>","retrieved":1655460965220},{"title":"undefined (멜론 ─ 최신앨범 ─ 국내)","contents":"<a href=\"javascript:melon.link.goArtistDetail('1703261');\" title=\"GENE_SIS OST part 1: D_COMPOSE 페이지 이동\" class=\"ellipsis\">Lil Cherry</a>","retrieved":1655460965225},{"title":"DNA 싱어 - 판타스틱 패밀리 Round 2&3 (멜론 ─ 최신앨범 ─ 국내)","contents":"<div class=\"thumb\">\n\t\t\t\t\t<a href=\"javascript:melon.link.goAlbumDetail('10985259');\" title=\"DNA 싱어 - 판타스틱 패밀리 Round 2&amp;3 - 페이지 이동\" class=\"image_typeAll\">\n\t\t\t\t\t\t<img onerror=\"WEBPOCIMG.defaultAlbumImg(this);\" src=\"https://cdnimg.melon.co.kr/cm2/album/images/109/85/259/10985259_20220616163235_500.jpg/melon/resize/360/quality/80/optimize\" alt=\"\" width=\"180\" height=\"180\">\n\t\t\t\t\t\t<span class=\"bg_album_frame\"></span>\n\t\t\t\t\t</a>\n\t\t\t\t</div>\n\n\t\t\t\t\n\n\t\t\t\t<div class=\"entry\">\n\t\t\t\t\t<div class=\"info\">\n\t\t\t\t\t\t<span class=\"vdo_name\">[옴니버스]</span>\n\t\t\t\t\t\t<a href=\"javascript:melon.link.goAlbumDetail('10985259');\" class=\"ellipsis album_name\" title=\"DNA 싱어 - 판타스틱 패밀리 Round 2&amp;3 - 페이지 이동\">DNA 싱어 - 판타스틱 패밀리 Round 2&amp;3</a>\n\t\t\t\t\t\t<span class=\"ellipsis artist\">\n\t\t\t\t\t\t\tVarious Artists<span class=\"checkEllipsis\" style=\"display: none;\">Various Artists</span>\n\t\t\t\t\t\t</span>\n\t\t\t\t\t\t\n\t\t\t\t\t</div>\n\t\t\t\t\t<div class=\"meta\">\n\t\t\t\t\t\t<span class=\"reg_date\" title=\"발매일\">2022.06.17</span>\n\t\t\t\t\t\t<i class=\"bar\"></i>\n\t\t\t\t\t\t<button type=\"button\" class=\"button_etc like\" title=\"DNA 싱어 - 판타스틱 패밀리 Round 2&amp;3 좋아요\" data-album-no=\"10985259\" data-album-menuid=\"18020123\"><span class=\"odd_span\">좋아요</span>\n<span class=\"cnt\"><strong class=\"none\">총건수</strong>19</span></button>\n\t\t\t\t\t\t<i class=\"bar\"></i>\n\t\t\t\t\t\t<span class=\"tot_song\" title=\"총 수록곡\">11곡</span>\n\t\t\t\t\t</div>\n\t\t\t\t\t<div class=\"wrap_btn_tb\">\n\t\t\t\t\t\t<button type=\"button\" onclick=\"melon.play.playAlbum('18020123','10985259');\" title=\"앨범듣기\" class=\"button_rbox\"><span class=\"button_icons type02 play\"></span><span class=\"cnt\">앨범듣기</span></button>\n\t\t\t\t\t\t<button type=\"button\" onclick=\"melon.buy.goBuyProduct('frm','10985259','3B0001','','0','18020123','1');\" title=\"앨범 다운로드\" class=\"button_rbox\"><span class=\"button_icons type02 download\"></span><span class=\"cnt\">앨범다운</span></button>\n\t\t\t\t\t\t\n\t\t\t\t\t\t<button type=\"button\" onclick=\"melon.buy.goPresentForAlbum('10985259', '', '18020123');\" title=\"선택된 곡 선물하기\" class=\"button_rbox\"><span class=\"button_icons type02 gift\"></span><span class=\"cnt\">선물</span></button>\n\t\t\t\t\t\t\n\t\t\t\t\t</div>\n\t\t\t\t</div>","link":"javascript:melon.link.goAlbumDetail('10985259');","retrieved":1655436429096,"image":"https://cdnimg.melon.co.kr/cm2/album/images/109/85/259/10985259_20220616163235_500.jpg/melon/resize/360/quality/80/optimize"},{"title":"Stupid Cool (멜론 ─ 최신앨범 ─ 국내)","contents":"던 (DAWN)","link":"javascript:melon.link.goAlbumDetail('10984701');","retrieved":1655374582014,"image":"https://cdnimg.melon.co.kr/cm2/album/images/109/84/701/10984701_20220615195830_500.jpg/melon/resize/360/quality/80/optimize"},{"title":"체인지데이즈 OST (멜론 ─ 최신앨범 ─ 국내)","contents":"YELO (옐로)","link":"javascript:melon.link.goAlbumDetail('10984677');","retrieved":1655374582026,"image":"https://cdnimg.melon.co.kr/cm2/album/images/109/84/677/10984677_20220615183005_500.jpg/melon/resize/360/quality/80/optimize"},{"title":"우리의 장면 (멜론 ─ 최신앨범 ─ 국내)","contents":"마리슈","link":"javascript:melon.link.goAlbumDetail('10985095');","retrieved":1655436429120,"image":"https://cdnimg.melon.co.kr/cm2/album/images/109/85/095/10985095_20220616144756_500.jpg/melon/resize/360/quality/80/optimize"},{"title":"수제버거 알바생의 고백 (멜론 ─ 최신앨범 ─ 국내)","contents":"를 (LEL)","link":"javascript:melon.link.goAlbumDetail('10985436');","retrieved":1655436429120,"image":"https://cdnimg.melon.co.kr/cm2/album/images/109/85/436/10985436_20220617101753_500.jpg/melon/resize/360/quality/80/optimize"},{"title":"CHAPTER 1 (멜론 ─ 최신앨범 ─ 국내)","contents":"권디엘(iamdl)","link":"javascript:melon.link.goAlbumDetail('10984510');","retrieved":1655436429120,"image":"https://cdnimg.melon.co.kr/cm2/album/images/109/84/510/10984510_20220615155852_500.jpg/melon/resize/360/quality/80/optimize"},{"title":"Summer In Love (멜론 ─ 최신앨범 ─ 국내)","contents":"SAAY","link":"javascript:melon.link.goAlbumDetail('10984826');","retrieved":1655374582026,"image":"https://cdnimg.melon.co.kr/cm2/album/images/109/84/826/10984826_20220616103919_500.jpg/melon/resize/360/quality/80/optimize"},{"title":"미영 (멜론 ─ 최신앨범 ─ 국내)","contents":"돕덕 (DopeDoug)","link":"javascript:melon.link.goAlbumDetail('10983122');","retrieved":1655436429124,"image":"https://cdnimg.melon.co.kr/cm2/album/images/109/83/122/10983122_20220614161520_500.jpg/melon/resize/360/quality/80/optimize"},{"title":"소나기 (멜론 ─ 최신앨범 ─ 국내)","contents":"이주영","link":"javascript:melon.link.goAlbumDetail('10985073');","retrieved":1655436429138,"image":"https://cdnimg.melon.co.kr/cm2/album/images/109/85/073/10985073_20220616143405_500.jpg/melon/resize/360/quality/80/optimize"},{"title":"AFTER, SEND IN THE MOON (멜론 ─ 최신앨범 ─ 국내)","contents":"STUDIO SNOW","link":"javascript:melon.link.goAlbumDetail('10985194');","retrieved":1655436429145,"image":"https://cdnimg.melon.co.kr/cm2/album/images/109/85/194/10985194_20220616153600_500.jpg/melon/resize/360/quality/80/optimize"},{"title":"품 (멜론 ─ 최신앨범 ─ 국내)","contents":"포유류 (PO.U.RYU)","link":"javascript:melon.link.goAlbumDetail('10984844');","retrieved":1655436429145,"image":"https://cdnimg.melon.co.kr/cm2/album/images/109/84/844/10984844_20220616110719_500.jpg/melon/resize/360/quality/80/optimize"},{"title":"DOWN (멜론 ─ 최신앨범 ─ 국내)","contents":"creespy","link":"javascript:melon.link.goAlbumDetail('10985364');","retrieved":1655436429146,"image":"https://cdnimg.melon.co.kr/cm2/album/images/109/85/364/10985364_20220616181125_500.jpg/melon/resize/360/quality/80/optimize"}]}