{"title":"Combined feed","url":"https://MusicReleaseKR.github.io/melon/all.xml","elements":[{"title":"HOW? (멜론 ─ 최신앨범 ─ 국내)","contents":"BOYNEXTDOOR","link":"javascript:melon.link.goAlbumDetail('11465011');","retrieved":1713172336624,"image":"https://cdnimg.melon.co.kr/cm2/album/images/114/65/011/11465011_20240415102247_500.jpg/melon/resize/360/quality/80/optimize"},{"title":"이별 자서전 (멜론 ─ 최신앨범 ─ 국내)","contents":"김나영","link":"javascript:melon.link.goAlbumDetail('11465012');","retrieved":1713172336625,"image":"https://cdnimg.melon.co.kr/cm2/album/images/114/65/012/11465012_20240415102455_500.jpg/melon/resize/360/quality/80/optimize"},{"title":"한 정거장 더 가서 내릴래요 (멜론 ─ 최신앨범 ─ 국내)","contents":"폴킴","link":"javascript:melon.link.goAlbumDetail('11463707');","retrieved":1713172336627,"image":"https://cdnimg.melon.co.kr/cm2/album/images/114/63/707/11463707_20240412132449_500.jpg/melon/resize/360/quality/80/optimize"},{"title":"undefined (멜론 ─ 최신앨범 ─ 국내)","contents":"<a href=\"javascript:melon.link.goArtistDetail('752425');\" title=\"한 정거장 더 가서 내릴래요 페이지 이동\" class=\"ellipsis\">폴킴</a>","retrieved":1713215590257},{"title":"undefined (멜론 ─ 최신앨범 ─ 국내)","contents":"<a href=\"javascript:melon.link.goArtistDetail('749451');\" title=\"한 정거장 더 가서 내릴래요 페이지 이동\" class=\"ellipsis\">한지민</a>","retrieved":1713215590262},{"title":"One Of A Kind (멜론 ─ 최신앨범 ─ 국내)","contents":"Loossemble (루셈블)","link":"javascript:melon.link.goAlbumDetail('11465068');","retrieved":1713172336628,"image":"https://cdnimg.melon.co.kr/cm2/album/images/114/65/068/11465068_20240415104600_500.jpg/melon/resize/360/quality/80/optimize"},{"title":"자로는 잴 수 없는 우리 사이 (매일 재회해 드립니다 X 이민혁) (멜론 ─ 최신앨범 ─ 국내)","contents":"이민혁","link":"javascript:melon.link.goAlbumDetail('11463654');","retrieved":1713172336630,"image":"https://cdnimg.melon.co.kr/cm2/album/images/114/63/654/11463654_20240412114756_500.jpg/melon/resize/360/quality/80/optimize"},{"title":"Zz (멜론 ─ 최신앨범 ─ 국내)","contents":"니브 (NIve)","link":"javascript:melon.link.goAlbumDetail('11465241');","retrieved":1713172336634,"image":"https://cdnimg.melon.co.kr/cm2/album/images/114/65/241/11465241_20240415141510_500.jpg/melon/resize/360/quality/80/optimize"},{"title":"Tough Love (멜론 ─ 최신앨범 ─ 국내)","contents":"유권 (블락비)","link":"javascript:melon.link.goAlbumDetail('11463631');","retrieved":1713172336635,"image":"https://cdnimg.melon.co.kr/cm2/album/images/114/63/631/11463631_20240412113605_500.jpg/melon/resize/360/quality/80/optimize"},{"title":"YEPPY (Korean Ver.) (멜론 ─ 최신앨범 ─ 국내)","contents":"키세스 (KISSXS)","link":"javascript:melon.link.goAlbumDetail('11463715');","retrieved":1713172336637,"image":"https://cdnimg.melon.co.kr/cm2/album/images/114/63/715/11463715_20240412133348_500.jpg/melon/resize/360/quality/80/optimize"},{"title":"2024 최강야구 OST (멜론 ─ 최신앨범 ─ 국내)","contents":"이원석","link":"javascript:melon.link.goAlbumDetail('11463706');","retrieved":1713172336644,"image":"https://cdnimg.melon.co.kr/cm2/album/images/114/63/706/11463706_20240412132447_500.jpg/melon/resize/360/quality/80/optimize"},{"title":"blue in my room (멜론 ─ 최신앨범 ─ 국내)","contents":"숨비","link":"javascript:melon.link.goAlbumDetail('11463630');","retrieved":1713172336645,"image":"https://cdnimg.melon.co.kr/cm2/album/images/114/63/630/11463630_20240412113555_500.jpg/melon/resize/360/quality/80/optimize"},{"title":"If i love that (멜론 ─ 최신앨범 ─ 국내)","contents":"104 (백사)","link":"javascript:melon.link.goAlbumDetail('11463629');","retrieved":1713172336646,"image":"https://cdnimg.melon.co.kr/cm2/album/images/114/63/629/11463629_20240412113552_500.jpg/melon/resize/360/quality/80/optimize"},{"title":"靑春, FANTASY (멜론 ─ 최신앨범 ─ 국내)","contents":"기프트 (GIFT)","link":"javascript:melon.link.goAlbumDetail('11463634');","retrieved":1713152090538,"image":"https://cdnimg.melon.co.kr/cm2/album/images/114/63/634/11463634_20240412114006_500.jpg/melon/resize/360/quality/80/optimize"},{"title":"시간이 필요했을 뿐이란 걸 (멜론 ─ 최신앨범 ─ 국내)","contents":"하모나이즈","link":"javascript:melon.link.goAlbumDetail('11463916');","retrieved":1713152090545,"image":"https://cdnimg.melon.co.kr/cm2/album/images/114/63/916/11463916_20240412145447_500.jpg/melon/resize/360/quality/80/optimize"},{"title":"Painful heart (멜론 ─ 최신앨범 ─ 국내)","contents":"406호 프로젝트","link":"javascript:melon.link.goAlbumDetail('11463614');","retrieved":1713152090546,"image":"https://cdnimg.melon.co.kr/cm2/album/images/114/63/614/11463614_20240412133930_500.jpg/melon/resize/360/quality/80/optimize"},{"title":"PUNK HOT (멜론 ─ 최신앨범 ─ 국내)","contents":"1CHU (원츄)","link":"javascript:melon.link.goAlbumDetail('11463697');","retrieved":1713152090550,"image":"https://cdnimg.melon.co.kr/cm2/album/images/114/63/697/11463697_20240412120954_500.jpg/melon/resize/360/quality/80/optimize"},{"title":"술래 (멜론 ─ 최신앨범 ─ 국내)","contents":"유수 (U_Soo)","link":"javascript:melon.link.goAlbumDetail('11463531');","retrieved":1713152090551,"image":"https://cdnimg.melon.co.kr/cm2/album/images/114/63/531/11463531_20240412111643_500.jpg/melon/resize/360/quality/80/optimize"},{"title":"수지맞은 우리 OST Part.4 (멜론 ─ 최신앨범 ─ 국내)","contents":"새라","link":"javascript:melon.link.goAlbumDetail('11463469');","retrieved":1713152090552,"image":"https://cdnimg.melon.co.kr/cm2/album/images/114/63/469/11463469_20240412110011_500.jpg/melon/resize/360/quality/80/optimize"},{"title":"undefined (멜론 ─ 최신앨범 ─ 국내)","contents":"<a href=\"javascript:melon.link.goArtistDetail('1702258');\" title=\"수지맞은 우리 OST Part.4 페이지 이동\" class=\"ellipsis\">새라</a>","retrieved":1713215590270},{"title":"undefined (멜론 ─ 최신앨범 ─ 국내)","contents":"<a href=\"javascript:melon.link.goArtistDetail('828501');\" title=\"수지맞은 우리 OST Part.4 페이지 이동\" class=\"ellipsis\">이한울</a>","retrieved":1713215590273},{"title":"MY HOLIDAY IS AFTER I DIE (멜론 ─ 최신앨범 ─ 국내)","contents":"Jade Lump","link":"javascript:melon.link.goAlbumDetail('11463705');","retrieved":1713152090554,"image":"https://cdnimg.melon.co.kr/cm2/album/images/114/63/705/11463705_20240412132400_500.jpg/melon/resize/360/quality/80/optimize"},{"title":"undefined (멜론 ─ 최신앨범 ─ 국내)","contents":"<a href=\"javascript:melon.link.goArtistDetail('3121550');\" title=\"MY HOLIDAY IS AFTER I DIE 페이지 이동\" class=\"ellipsis\">Jade Lump</a>","retrieved":1713215590273},{"title":"undefined (멜론 ─ 최신앨범 ─ 국내)","contents":"<a href=\"javascript:melon.link.goArtistDetail('3750240');\" title=\"MY HOLIDAY IS AFTER I DIE 페이지 이동\" class=\"ellipsis\">LAPAEL</a>","retrieved":1713215590279},{"title":"귀인 (멜론 ─ 최신앨범 ─ 국내)","contents":"은가은","link":"javascript:melon.link.goAlbumDetail('11463901');","retrieved":1713152090555,"image":"https://cdnimg.melon.co.kr/cm2/album/images/114/63/901/11463901_20240415103912_500.jpg/melon/resize/360/quality/80/optimize"},{"title":"Missed Me? (멜론 ─ 최신앨범 ─ 국내)","contents":"h3re (히어)","link":"javascript:melon.link.goAlbumDetail('11465006');","retrieved":1713152090557,"image":"https://cdnimg.melon.co.kr/cm2/album/images/114/65/006/11465006_20240415101546_500.jpg/melon/resize/360/quality/80/optimize"}]}