{"title":"Combined feed","url":"https://MusicReleaseKR.github.io/melon/all.xml","elements":[{"title":"낮에 뜨는 달 OST Part.3 (멜론 ─ 최신앨범 ─ 국내)","contents":"이바다","link":"javascript:melon.link.goAlbumDetail('11366484');","retrieved":1700104408921,"image":"https://cdnimg.melon.co.kr/cm2/album/images/113/66/484/11366484_20231115163712_500.jpg/melon/resize/360/quality/80/optimize"},{"title":"필로소피 (멜론 ─ 최신앨범 ─ 국내)","contents":"알레프 (ALEPH)","link":"javascript:melon.link.goAlbumDetail('11365549');","retrieved":1700104408923,"image":"https://cdnimg.melon.co.kr/cm2/album/images/113/65/549/11365549_20231115135354_500.jpg/melon/resize/360/quality/80/optimize"},{"title":"트랄랄라 브라더스 베스트 PART25 (멜론 ─ 최신앨범 ─ 국내)","contents":"<div class=\"thumb\">\n\t\t\t\t\t<a href=\"javascript:melon.link.goAlbumDetail('11366088');\" title=\"트랄랄라 브라더스 베스트 PART25 - 페이지 이동\" class=\"image_typeAll\">\n\t\t\t\t\t\t<img onerror=\"WEBPOCIMG.defaultAlbumImg(this);\" width=\"180\" height=\"180\" src=\"https://cdnimg.melon.co.kr/cm2/album/images/113/66/088/11366088_20231115153702_500.jpg/melon/resize/360/quality/80/optimize\" alt=\"\">\n\t\t\t\t\t\t<span class=\"bg_album_frame\"></span>\n\t\t\t\t\t</a>\n\t\t\t\t</div>\n\n\t\t\t\t\n\n\t\t\t\t<div class=\"entry\">\n\t\t\t\t\t<div class=\"info\">\n\t\t\t\t\t\t<span class=\"vdo_name\">[옴니버스]</span>\n\t\t\t\t\t\t<a href=\"javascript:melon.link.goAlbumDetail('11366088');\" class=\"ellipsis album_name\" title=\"트랄랄라 브라더스 베스트 PART25 - 페이지 이동\">트랄랄라 브라더스 베스트 PART25</a>\n\t\t\t\t\t\t<span class=\"ellipsis artist\">\n\t\t\t\t\t\t\tVarious Artists<span class=\"checkEllipsis\" style=\"display: none;\">Various Artists</span>\n\t\t\t\t\t\t</span>\n\t\t\t\t\t\t\n\t\t\t\t\t</div>\n\t\t\t\t\t<div class=\"meta\">\n\t\t\t\t\t\t<span class=\"reg_date\" title=\"발매일\">2023.11.16</span>\n\t\t\t\t\t\t<i class=\"bar\"></i>\n\t\t\t\t\t\t<button type=\"button\" class=\"button_etc like\" title=\"트랄랄라 브라더스 베스트 PART25 좋아요\" data-album-no=\"11366088\" data-album-menuid=\"18020123\"><span class=\"odd_span\">좋아요</span>\n<span class=\"cnt\"><strong class=\"none\">총건수</strong>59</span></button>\n\t\t\t\t\t\t<i class=\"bar\"></i>\n\t\t\t\t\t\t<span class=\"tot_song\" title=\"총 수록곡\">4곡</span>\n\t\t\t\t\t</div>\n\t\t\t\t\t<div class=\"wrap_btn_tb\">\n\t\t\t\t\t\t<button type=\"button\" onclick=\"melon.play.playAlbum('18020123','11366088');\" title=\"앨범듣기\" class=\"button_rbox\"><span class=\"button_icons type02 play\"></span><span class=\"cnt\">앨범듣기</span></button>\n\t\t\t\t\t\t<button type=\"button\" onclick=\"melon.buy.goBuyProduct('frm','11366088','3B0001','','0','18020123','1');\" title=\"앨범 다운로드\" class=\"button_rbox\"><span class=\"button_icons type02 download\"></span><span class=\"cnt\">앨범다운</span></button>\n\t\t\t\t\t\t\n\t\t\t\t\t\t<button type=\"button\" onclick=\"melon.buy.goPresentForAlbum('11366088', '', '18020123');\" title=\"선택된 곡 선물하기\" class=\"button_rbox\"><span class=\"button_icons type02 gift\"></span><span class=\"cnt\">선물</span></button>\n\t\t\t\t\t\t\n\t\t\t\t\t</div>\n\t\t\t\t</div>","link":"javascript:melon.link.goAlbumDetail('11366088');","retrieved":1700104408916,"image":"https://cdnimg.melon.co.kr/cm2/album/images/113/66/088/11366088_20231115153702_500.jpg/melon/resize/360/quality/80/optimize"},{"title":"지극히 사적인 얘기 (멜론 ─ 최신앨범 ─ 국내)","contents":"다비치","link":"javascript:melon.link.goAlbumDetail('11364396');","retrieved":1700039607826,"image":"https://cdnimg.melon.co.kr/cm2/album/images/113/64/396/11364396_20231114104345_500.jpg/melon/resize/360/quality/80/optimize"},{"title":"그림자 괴물 (멜론 ─ 최신앨범 ─ 국내)","contents":"유자","link":"javascript:melon.link.goAlbumDetail('11365944');","retrieved":1700104408928,"image":"https://cdnimg.melon.co.kr/cm2/album/images/113/65/944/11365944_20231115150705_500.jpg/melon/resize/360/quality/80/optimize"},{"title":"Warming Up (멜론 ─ 최신앨범 ─ 국내)","contents":"말든 (Marldn)","link":"javascript:melon.link.goAlbumDetail('11365957');","retrieved":1700104408929,"image":"https://cdnimg.melon.co.kr/cm2/album/images/113/65/957/11365957_20231115151258_500.jpg/melon/resize/360/quality/80/optimize"},{"title":"AMPERSAND ONE (멜론 ─ 최신앨범 ─ 국내)","contents":"앰퍼샌드원 (AMPERS&amp;ONE)","link":"javascript:melon.link.goAlbumDetail('11364779');","retrieved":1700039607827,"image":"https://cdnimg.melon.co.kr/cm2/album/images/113/64/779/11364779_20231114152348_500.jpg/melon/resize/360/quality/80/optimize"},{"title":"Stay High (멜론 ─ 최신앨범 ─ 국내)","contents":"Kim Addict (킴 애딕)","link":"javascript:melon.link.goAlbumDetail('11366725');","retrieved":1700104408933,"image":"https://cdnimg.melon.co.kr/cm2/album/images/113/66/725/11366725_20231115175201_500.jpg/melon/resize/360/quality/80/optimize"},{"title":"Good time (Prod. RYUKIE) (멜론 ─ 최신앨범 ─ 국내)","contents":"미래","link":"javascript:melon.link.goAlbumDetail('11365782');","retrieved":1700104408934,"image":"https://cdnimg.melon.co.kr/cm2/album/images/113/65/782/11365782_20231115143443_500.jpg/melon/resize/360/quality/80/optimize"},{"title":"회상<산울림 50주년 기념 프로젝트〉 (멜론 ─ 최신앨범 ─ 국내)","contents":"롤링쿼츠 (Rolling Quartz)","link":"javascript:melon.link.goAlbumDetail('11366488');","retrieved":1700104408936,"image":"https://cdnimg.melon.co.kr/cm2/album/images/113/66/488/11366488_20231115163907_500.jpg/melon/resize/360/quality/80/optimize"},{"title":"EMBERS (멜론 ─ 최신앨범 ─ 국내)","contents":"이스트샤인 (EASTSHINE)","link":"javascript:melon.link.goAlbumDetail('11365551');","retrieved":1700104408937,"image":"https://cdnimg.melon.co.kr/cm2/album/images/113/65/551/11365551_20231115135845_500.jpg/melon/resize/360/quality/80/optimize"},{"title":"밤의 품에 (Feat. 범키) (멜론 ─ 최신앨범 ─ 국내)","contents":"야루","link":"javascript:melon.link.goAlbumDetail('11366644');","retrieved":1700104408938,"image":"https://cdnimg.melon.co.kr/cm2/album/images/113/66/644/11366644_20231115171837_500.jpg/melon/resize/360/quality/80/optimize"},{"title":"잉어님과 떡볶이 OST Part.22 (멜론 ─ 최신앨범 ─ 국내)","contents":"천소아 (Cheon Soa)","link":"javascript:melon.link.goAlbumDetail('11364393');","retrieved":1700104408939,"image":"https://cdnimg.melon.co.kr/cm2/album/images/113/64/393/11364393_20231114103949_500.jpg/melon/resize/360/quality/80/optimize"},{"title":"텔레파시 (멜론 ─ 최신앨범 ─ 국내)","contents":"혹시몰라","link":"javascript:melon.link.goAlbumDetail('11366735');","retrieved":1700104408940,"image":"https://cdnimg.melon.co.kr/cm2/album/images/113/66/735/11366735_20231115175743_500.jpg/melon/resize/360/quality/80/optimize"},{"title":"OOPS (멜론 ─ 최신앨범 ─ 국내)","contents":"비버 (Beaver)","link":"javascript:melon.link.goAlbumDetail('11365947');","retrieved":1700104408942,"image":"https://cdnimg.melon.co.kr/cm2/album/images/113/65/947/11365947_20231115150846_500.jpg/melon/resize/360/quality/80/optimize"},{"title":"오늘도 사랑스럽개 OST Part. 2 : 타이밍 (멜론 ─ 최신앨범 ─ 국내)","contents":"민니 ((여자)아이들)","link":"javascript:melon.link.goAlbumDetail('11364837');","retrieved":1700039607830,"image":"https://cdnimg.melon.co.kr/cm2/album/images/113/64/837/11364837_20231114171136_500.jpg/melon/resize/360/quality/80/optimize"},{"title":"現像 : 소년의 파란 (멜론 ─ 최신앨범 ─ 국내)","contents":"기욱 (ONEWE)","link":"javascript:melon.link.goAlbumDetail('11364835');","retrieved":1700039607834,"image":"https://cdnimg.melon.co.kr/cm2/album/images/113/64/835/11364835_20231114171001_500.jpg/melon/resize/360/quality/80/optimize"},{"title":"Murmur of Earth (멜론 ─ 최신앨범 ─ 국내)","contents":"욘 (오정수)","link":"javascript:melon.link.goAlbumDetail('11366716');","retrieved":1700104408946,"image":"https://cdnimg.melon.co.kr/cm2/album/images/113/66/716/11366716_20231115174905_500.jpg/melon/resize/360/quality/80/optimize"},{"title":"뚜껑별꽃 (멜론 ─ 최신앨범 ─ 국내)","contents":"윤도현","link":"javascript:melon.link.goAlbumDetail('11365460');","retrieved":1700039607841,"image":"https://cdnimg.melon.co.kr/cm2/album/images/113/65/460/11365460_20231115120702_500.jpg/melon/resize/360/quality/80/optimize"},{"title":"너를 보낸다 (멜론 ─ 최신앨범 ─ 국내)","contents":"Kid Wine","link":"javascript:melon.link.goAlbumDetail('11364667');","retrieved":1700039607846,"image":"https://cdnimg.melon.co.kr/cm2/album/images/113/64/667/11364667_20231114135556_500.jpg/melon/resize/360/quality/80/optimize"}]}